odoo/addons/product_matrix_sticky_header/README.rst
odoo/addons/product_matrix_sticky_header/__init__.py
odoo/addons/product_matrix_sticky_header/__manifest__.py
odoo/addons/product_matrix_sticky_header/i18n/product_matrix_sticky_header.pot
odoo/addons/product_matrix_sticky_header/readme/CONFIGURATION.rst
odoo/addons/product_matrix_sticky_header/readme/CONTRIBUTORS.rst
odoo/addons/product_matrix_sticky_header/readme/DESCRIPTION.rst
odoo/addons/product_matrix_sticky_header/readme/ROADMAP.rst
odoo/addons/product_matrix_sticky_header/readme/USAGE.rst
odoo/addons/product_matrix_sticky_header/static/description/icon.png
odoo/addons/product_matrix_sticky_header/static/description/index.html
odoo/addons/product_matrix_sticky_header/static/img/screenshot.gif
odoo/addons/product_matrix_sticky_header/static/src/js/section_and_note_widget.js
odoo/addons/product_matrix_sticky_header/static/src/scss/product_matrix.scss
odoo/addons/product_matrix_sticky_header/static/src/xml/product_matrix.xml
odoo/addons/product_matrix_sticky_header/views/assets.xml
odoo14_addon_product_matrix_sticky_header-14.0.1.0.1.dist-info/METADATA
odoo14_addon_product_matrix_sticky_header-14.0.1.0.1.dist-info/WHEEL
odoo14_addon_product_matrix_sticky_header-14.0.1.0.1.dist-info/top_level.txt
odoo14_addon_product_matrix_sticky_header-14.0.1.0.1.dist-info/RECORD
