Metadata-Version: 2.1
Name: odoo14-addon-product-matrix-sticky-header
Version: 14.0.1.0.1
Summary: Technical module: Add sticky header for Matrix Product
Home-page: https://github.com/OCA/product-variant
Author: Studio73,Odoo Community Association (OCA)
Author-email: support@odoo-community.org
License: LGPL-3
Platform: UNKNOWN
Classifier: Programming Language :: Python
Classifier: Framework :: Odoo
Classifier: Framework :: Odoo :: 14.0
Classifier: License :: OSI Approved :: GNU Lesser General Public License v3 (LGPLv3)
Requires-Python: >=3.6
Requires-Dist: odoo <14.1dev,>=14.0a
